langgraph_func/README.md
langgraph_func/__init__.py
langgraph_func/config.py
langgraph_func/docs_builder.py
langgraph_func/docs_html/01-graph-structure.html
langgraph_func/docs_html/02-deployment.html
langgraph_func/docs_html/03-yaml-function-app.html
langgraph_func/docs_html/04-helper-functions.html
langgraph_func/docs_html/_sources/01-graph-structure.md.txt
langgraph_func/docs_html/_sources/02-deployment.md.txt
langgraph_func/docs_html/_sources/03-yaml-function-app.md.txt
langgraph_func/docs_html/_sources/04-helper-functions.md.txt
langgraph_func/docs_html/_sources/index.rst.txt
langgraph_func/docs_html/_static/alabaster.css
langgraph_func/docs_html/_static/basic.css
langgraph_func/docs_html/_static/custom.css
langgraph_func/docs_html/_static/doctools.js
langgraph_func/docs_html/_static/documentation_options.js
langgraph_func/docs_html/_static/file.png
langgraph_func/docs_html/_static/github-banner.svg
langgraph_func/docs_html/_static/language_data.js
langgraph_func/docs_html/_static/minus.png
langgraph_func/docs_html/_static/plus.png
langgraph_func/docs_html/_static/pygments.css
langgraph_func/docs_html/_static/searchtools.js
langgraph_func/docs_html/_static/sphinx_highlight.js
langgraph_func/docs_html/genindex.html
langgraph_func/docs_html/index.html
langgraph_func/docs_html/objects.inv
langgraph_func/docs_html/search.html
langgraph_func/docs_html/searchindex.js
langgraph_func/files/swagger.html
langgraph_func/func_app_builder/__init__.py
langgraph_func/func_app_builder/blueprint_builder.py
langgraph_func/func_app_builder/create_app.py
langgraph_func/func_app_builder/func_app_builder.py
langgraph_func/graph_endpoints/__init__.py
langgraph_func/graph_endpoints/graph_executor_factory.py
langgraph_func/graph_endpoints/graph_executor_service.py
langgraph_func/graph_endpoints/registry.py
langgraph_func/graph_helpers/__init__.py
langgraph_func/graph_helpers/call_subgraph.py
langgraph_func/graph_helpers/graph_builder_helpers.py
langgraph_func/graph_helpers/wrappers.py
langgraph_func-0.3.9.dist-info/METADATA
langgraph_func-0.3.9.dist-info/WHEEL
langgraph_func-0.3.9.dist-info/RECORD
