Metadata-Version: 2.3
Name: langgraph_func
Version: 0.3.9
Summary: LangGraph Azure Function Agents
Author: job van Creij jobvancreij@gmail.com
Requires-Python: >=3.10,<4.0
Classifier: Programming Language :: Python :: 3
Classifier: Programming Language :: Python :: 3.10
Classifier: Programming Language :: Python :: 3.11
Classifier: Programming Language :: Python :: 3.12
Classifier: Programming Language :: Python :: 3.13
Requires-Dist: azure-functions
Requires-Dist: dacite
Requires-Dist: langgraph
Requires-Dist: openapi-schema-pydantic
Requires-Dist: pydantic
Requires-Dist: requests
Project-URL: Documentation, https://jobaibv.github.io/langgraph_func/
